{"id":19867601, "version":1, "data": {"behavior":{"v":"2","nodes":[{"inputCount":0,"outputCount":0,"name":"Animaation","behaviorType":"logic.NodeGroup","x":-90,"y":-16,"group":"","id":"1b04c6ef9b997941","isMenuItem":false},{"inputCount":0,"outputCount":1,"name":"Once","behaviorType":"logic.triggers.Once","x":-630,"y":-720,"group":"1b04c6ef9b997941","id":"1b04c6f0af11d24d","resetOnLevelStart":false},{"inputCount":6,"outputCount":2,"name":"Ease","behaviorType":"logic.logic.Ease2","x":-450,"y":-768,"group":"1b04c6ef9b997941","id":"1b04c6f0dc7c4b4f","duration":2,"from":0,"to":100,"easeFunc":"Sine","easeType":1,"smartRot":true},{"inputCount":0,"outputCount":4,"name":"MouseClick","behaviorType":"logic.triggers.MouseClick","x":-180,"y":-576,"group":"1b04c6ef9b997941","id":"1b04e1ac92da7344","global":false,"skipAlpha":false},{"inputCount":3,"outputCount":3,"name":"Size","behaviorType":"logic.properties.Scale","x":-270,"y":-752,"group":"1b04c6ef9b997941","id":"1b1857b183b5054d"},{"inputCount":2,"outputCount":2,"name":"LoadLevel","behaviorType":"logic.gameflow.NextLevel","x":0,"y":-704,"group":"1b04c6ef9b997941","id":"1b187a71bbcf0c4e","levelId":0}],"links":[{"input_id":"1b04c6f0dc7c4b4fi3","output_id":"1b04c6f0af11d24do0"},{"input_id":"1b04c6f0dc7c4b4fi4","output_id":"1b04e1ac92da7344o0"},{"input_id":"1b1857b183b5054di0","output_id":"1b04c6f0dc7c4b4fo0"},{"input_id":"1b187a71bbcf0c4ei1","output_id":"1b1857b183b5054do0"},{"input_id":"1b187a71bbcf0c4ei0","output_id":"1b04e1ac92da7344o0"}]}}}